MANIFEST.in
setup.py
test.py
.lib/distutils-precedence.pth
.lib/_distutils_hack/__init__.py
.lib/_distutils_hack/override.py
.lib/about/Trove-classifiers.txt
.lib/about/__init__.py
.lib/about/about.py
.lib/about-5.2.dist-info/INSTALLER
.lib/about-5.2.dist-info/LICENSE.txt
.lib/about-5.2.dist-info/METADATA
.lib/about-5.2.dist-info/RECORD
.lib/about-5.2.dist-info/REQUESTED
.lib/about-5.2.dist-info/WHEEL
.lib/about-5.2.dist-info/pbr.json
.lib/about-5.2.dist-info/top_level.txt
.lib/pkg_resources/__init__.py
.lib/pkg_resources/_vendor/__init__.py
.lib/pkg_resources/_vendor/typing_extensions.py
.lib/pkg_resources/_vendor/zipp.py
.lib/pkg_resources/_vendor/importlib_resources/__init__.py
.lib/pkg_resources/_vendor/importlib_resources/_adapters.py
.lib/pkg_resources/_vendor/importlib_resources/_common.py
.lib/pkg_resources/_vendor/importlib_resources/_compat.py
.lib/pkg_resources/_vendor/importlib_resources/_itertools.py
.lib/pkg_resources/_vendor/importlib_resources/_legacy.py
.lib/pkg_resources/_vendor/importlib_resources/abc.py
.lib/pkg_resources/_vendor/importlib_resources/readers.py
.lib/pkg_resources/_vendor/importlib_resources/simple.py
.lib/pkg_resources/_vendor/jaraco/__init__.py
.lib/pkg_resources/_vendor/jaraco/context.py
.lib/pkg_resources/_vendor/jaraco/functools.py
.lib/pkg_resources/_vendor/jaraco/text/__init__.py
.lib/pkg_resources/_vendor/more_itertools/__init__.py
.lib/pkg_resources/_vendor/more_itertools/more.py
.lib/pkg_resources/_vendor/more_itertools/recipes.py
.lib/pkg_resources/_vendor/packaging/__init__.py
.lib/pkg_resources/_vendor/packaging/_elffile.py
.lib/pkg_resources/_vendor/packaging/_manylinux.py
.lib/pkg_resources/_vendor/packaging/_musllinux.py
.lib/pkg_resources/_vendor/packaging/_parser.py
.lib/pkg_resources/_vendor/packaging/_structures.py
.lib/pkg_resources/_vendor/packaging/_tokenizer.py
.lib/pkg_resources/_vendor/packaging/markers.py
.lib/pkg_resources/_vendor/packaging/metadata.py
.lib/pkg_resources/_vendor/packaging/requirements.py
.lib/pkg_resources/_vendor/packaging/specifiers.py
.lib/pkg_resources/_vendor/packaging/tags.py
.lib/pkg_resources/_vendor/packaging/utils.py
.lib/pkg_resources/_vendor/packaging/version.py
.lib/pkg_resources/_vendor/platformdirs/__init__.py
.lib/setuptools-68.1.2.dist-info/INSTALLER
.lib/setuptools-68.1.2.dist-info/LICENSE
.lib/setuptools-68.1.2.dist-info/METADATA
.lib/setuptools-68.1.2.dist-info/RECORD
.lib/setuptools-68.1.2.dist-info/WHEEL
.lib/setuptools-68.1.2.dist-info/entry_points.txt
.lib/setuptools-68.1.2.dist-info/top_level.txt
audio.coders.egg-info/PKG-INFO
audio.coders.egg-info/SOURCES.txt
audio.coders.egg-info/dependency_links.txt
audio.coders.egg-info/requires.txt
audio.coders.egg-info/top_level.txt