Metadata-Version: 2.1
Name: audio.coders
Version: 5.0.0
Summary: Unary and Rice codecs
Author: Sébastien Boisgérault
Author-email: Sebastien.Boisgerault@mines-paristech.fr
License: MIT License
